beiwe_forest-1.0.dist-info/licenses/LICENSE.md
forest/__init__.py
forest/constants.py
forest/utils.py
forest/bonsai/__init__.py
forest/bonsai/simulate_gps_data.py
forest/bonsai/simulate_log_data.py
forest/jasmine/__init__.py
forest/jasmine/data2mobmat.py
forest/jasmine/mobmat2traj.py
forest/jasmine/sogp_gps.py
forest/jasmine/traj2stats.py
forest/oak/__init__.py
forest/oak/base.py
forest/poplar/__init__.py
forest/poplar/classes/__init__.py
forest/poplar/classes/history.py
forest/poplar/classes/registry.py
forest/poplar/classes/template.py
forest/poplar/classes/trackers.py
forest/poplar/constants/__init__.py
forest/poplar/constants/misc.py
forest/poplar/constants/time.py
forest/poplar/functions/__init__.py
forest/poplar/functions/helpers.py
forest/poplar/functions/holidays.py
forest/poplar/functions/io.py
forest/poplar/functions/log.py
forest/poplar/functions/time.py
forest/poplar/functions/timezone.py
forest/poplar/legacy/__init__.py
forest/poplar/legacy/common_funcs.py
forest/poplar/raw/__init__.py
forest/poplar/raw/doc.py
forest/poplar/raw/readers.py
forest/poplar/raw/noncode/data_streams.csv
forest/poplar/raw/noncode/headers.json
forest/poplar/raw/noncode/power_events.csv
forest/poplar/raw/noncode/question_type_names.json
forest/sycamore/__init__.py
forest/sycamore/__main__.py
forest/sycamore/base.py
forest/sycamore/common.py
forest/sycamore/constants.py
forest/sycamore/read_audio.py
forest/sycamore/responses.py
forest/sycamore/submits.py
forest/sycamore/utils.py
forest/willow/__init__.py
forest/willow/log_stats.py
beiwe_forest-1.0.dist-info/METADATA
beiwe_forest-1.0.dist-info/WHEEL
beiwe_forest-1.0.dist-info/top_level.txt
beiwe_forest-1.0.dist-info/RECORD
