Metadata-Version: 2.4
Name: beiwe-forest
Version: 1.0
Summary: Forest is a library for analyzing smartphone-based high-throughput digital phenotyping data
Author: Jukka-Pekka Onnela, Josh Barback, Zachary Clement, Hassan Dawood, Georgios Efstathiadis, Patrick Emedom-Nnamdi, Emily J. Huang, Marta Karas, Gang Liu, Nellie Ponarul, Marcin Straczkiewicz, Ilya Sytchev, Anna Beukenhorst
Maintainer-email: Onnela Lab <onnela.lab@gmail.com>
License: BSD-3-Clause
Project-URL: Documentation, https://forest.beiwe.org
Project-URL: Homepage, https://forest.beiwe.org
Project-URL: Issues, https://github.com/onnela-lab/forest/issues
Project-URL: Source, https://github.com/onnela-lab/forest
Keywords: digital phenotyping,smartphone,statistics,accelerometer,GPS
Classifier: Development Status :: 4 - Beta
Classifier: Environment :: Console
Classifier: Intended Audience :: Science/Research
Classifier: License :: OSI Approved :: BSD License
Classifier: Natural Language :: English
Classifier: Operating System :: MacOS :: MacOS X
Classifier: Operating System :: Microsoft :: Windows
Classifier: Operating System :: POSIX :: Linux
Classifier: Programming Language :: Python :: 3
Classifier: Programming Language :: Python :: 3.11
Classifier: Programming Language :: Python :: 3.12
Classifier: Topic :: Scientific/Engineering :: Information Analysis
Requires-Python: >=3.11
License-File: LICENSE.md
Requires-Dist: holidays
Requires-Dist: librosa
Requires-Dist: numpy
Requires-Dist: openrouteservice
Requires-Dist: pandas
Requires-Dist: pyproj
Requires-Dist: python-dateutil
Requires-Dist: pytz
Requires-Dist: ratelimit
Requires-Dist: requests
Requires-Dist: scipy
Requires-Dist: shapely
Requires-Dist: ssqueezepy
Requires-Dist: timezonefinder
Provides-Extra: dev
Requires-Dist: build; extra == "dev"
Requires-Dist: cffconvert; extra == "dev"
Requires-Dist: flake8; extra == "dev"
Requires-Dist: flake8-pytest-style; extra == "dev"
Requires-Dist: mypy; extra == "dev"
Requires-Dist: pytest; extra == "dev"
Requires-Dist: pytest-mock; extra == "dev"
Requires-Dist: twine; extra == "dev"
Requires-Dist: types-python-dateutil; extra == "dev"
Requires-Dist: types-pytz; extra == "dev"
Requires-Dist: types-requests; extra == "dev"
Requires-Dist: types-setuptools; extra == "dev"
Dynamic: license-file
